{
  "logs": [
    {
      "file": "/logs/2023/05/0668_2023-05-29-1435.oao",
      "size": 76936,
      "timezone": 120,
      "mode": 0,
      "start_date": 1685363724000,
      "end_date": 1685364014000,
      "duration": 290000,
      "distance": 1410,
      "2s_best": 0,
      "10s_best": 0,
      "500m_best": 0,
      "1852m_best": 0,
      "a500m_best": 0,
      "1h_best": 0,
      "spot": "",
      "wind": "",
      "board": "",
      "sail": "",
      "fin": ""
    },
    {
      "file": "/logs/2023/06/0668_2023-06-18-1333.oao",
      "size": 333296,
      "timezone": 120,
      "mode": 0,
      "start_date": 1687087990000,
      "end_date": 1687089266000,
      "duration": 1276000,
      "distance": 15806,
      "2s_best": 0,
      "10s_best": 0,
      "500m_best": 0,
      "1852m_best": 0,
      "a500m_best": 0,
      "1h_best": 0,
      "spot": "",
      "wind": "",
      "board": "",
      "sail": "",
      "fin": ""
    },
    {
      "file": "/logs/2023/06/0668_2023-06-18-1342.oao",
      "size": 2420,
      "timezone": 60,
      "mode": 0,
      "start_date": 1687092120000,
      "end_date": 1687094970000,
      "duration": 2850000,
      "distance": 212895,
      "2s_best": 0,
      "10s_best": 0,
      "500m_best": 0,
      "1852m_best": 0,
      "a500m_best": 0,
      "1h_best": 0,
      "spot": "",
      "wind": "",
      "board": "",
      "sail": "",
      "fin": ""
    }
  ]
}