{
  "BUR104EMI_618_20221015_110600.oao": {
    "motion_file": "/logs/2022/10/0618_2022-10-15-1106.oao",
    "local_file": "/home/jovyan/work/sse-results/events/2022/gpslogs/20221015/BUR104EMI_618_20221015_110600.oao",
    "size": 1599080,
    "start_date": 1665828360000,
    "end_date": 1665852112000,
    "duration": 23752000,
    "distance": 55302113,
    "2s_best": 18473,
    "10s_best": 17910,
    "500m_best": 17521,
    "status": "completed"
  },
  "BUR104EMI_618_20221017_103816.oao": {
    "motion_file": "/logs/2022/10/0618_2022-10-17-1038.oao",
    "local_file": "/home/jovyan/work/sse-results/events/2022/gpslogs/20221017/BUR104EMI_618_20221017_103816.oao",
    "size": 1646348,
    "start_date": 1665999496000,
    "end_date": 1666015334000,
    "duration": 15838000,
    "distance": 54941304,
    "2s_best": 15276,
    "10s_best": 14924,
    "500m_best": 14517,
    "status": "completed"
  },
  "LON618JAM_618_20231007_102440.oao": {
    "motion_file": "/logs/2023/10/0618_2023-10-07-1024.oao",
    "local_file": "/home/jovyan/work/sse-results/events/2023/gpslogs/20231007/LON618JAM_618_20231007_102440.oao",
    "size": 1849200,
    "start_date": 1696670680000,
    "end_date": 1696689976000,
    "duration": 19296000,
    "distance": 65889373,
    "2s_best": 24509,
    "10s_best": 24201,
    "500m_best": 23533,
    "status": "completed"
  },
  "LON618JAM_618_20231010_094740.oao": {
    "motion_file": "/logs/2023/10/0618_2023-10-10-0947.oao",
    "local_file": "/home/jovyan/work/sse-results/events/2023/gpslogs/20231010/LON618JAM_618_20231010_094740.oao",
    "size": 2442364,
    "start_date": 1696927660000,
    "end_date": 1696951504000,
    "duration": 23844000,
    "distance": 88318212,
    "2s_best": 22135,
    "10s_best": 21449,
    "500m_best": 20220,
    "status": "completed"
  },
  "LON618JAM_618_20231011_101231.oao": {
    "motion_file": "/logs/2023/10/0618_2023-10-11-1012.oao",
    "local_file": "/home/jovyan/work/sse-results/events/2023/gpslogs/20231011/LON618JAM_618_20231011_101231.oao",
    "size": 2307372,
    "start_date": 1697015551000,
    "end_date": 1697036926000,
    "duration": 21375000,
    "distance": 80318550,
    "2s_best": 25181,
    "10s_best": 25118,
    "500m_best": 25034,
    "status": "completed"
  },
  "LON618JAM_618_20231012_102648.oao": {
    "motion_file": "/logs/2023/10/0618_2023-10-12-1026.oao",
    "local_file": "/home/jovyan/work/sse-results/events/2023/gpslogs/20231012/LON618JAM_618_20231012_102648.oao",
    "size": 93888,
    "start_date": 1697102808000,
    "end_date": 1697120360000,
    "duration": 17552000,
    "distance": 4945761,
    "2s_best": 22051,
    "10s_best": 21919,
    "500m_best": 21711,
    "status": "completed"
  },
  "LON618JAM_618_20231013_084316.oao": {
    "motion_file": "/logs/2023/10/0618_2023-10-13-0843.oao",
    "local_file": "/home/jovyan/work/sse-results/events/2023/gpslogs/20231013/LON618JAM_618_20231013_084316.oao",
    "size": 3077752,
    "start_date": 1697182996000,
    "end_date": 1697210926000,
    "duration": 27930000,
    "distance": 114232169,
    "2s_best": 22248,
    "10s_best": 21943,
    "500m_best": 21252,
    "status": "completed"
  },
  "GIB618JEN_618_20241012_104131.oao": {
    "motion_file": "/logs/2024/10/0618_2024-10-12-1041.oao",
    "local_file": "/home/jovyan/work/sse-results/events/2024/gpslogs/20241012/GIB618JEN_618_20241012_104131.oao",
    "size": 1248236,
    "start_date": 1728726091000,
    "end_date": 1728751119000,
    "duration": 25028000,
    "distance": 48372930,
    "2s_best": 15624,
    "10s_best": 15431,
    "500m_best": 15056,
    "status": "completed"
  },
  "GIB618JEN_618_20241014_095132.oao": {
    "motion_file": "/logs/2024/10/0618_2024-10-14-0951.oao",
    "local_file": "/home/jovyan/work/sse-results/events/2024/gpslogs/20241014/GIB618JEN_618_20241014_095132.oao",
    "size": 1835524,
    "start_date": 1728895892000,
    "end_date": 1728915557000,
    "duration": 19665000,
    "distance": 58255030,
    "2s_best": 13432,
    "10s_best": 13204,
    "500m_best": 12989,
    "status": "completed"
  },
  "GIB618JEN_618_20241015_094836.oao": {
    "motion_file": "/logs/2024/10/0618_2024-10-15-0948.oao",
    "local_file": "/home/jovyan/work/sse-results/events/2024/gpslogs/20241015/GIB618JEN_618_20241015_094836.oao",
    "size": 1907232,
    "start_date": 1728982116000,
    "end_date": 1729008863000,
    "duration": 26747000,
    "distance": 78167856,
    "2s_best": 15596,
    "10s_best": 15230,
    "500m_best": 15024,
    "status": "completed"
  },
  "GIB618JEN_618_20241016_094643.oao": {
    "motion_file": "/logs/2024/10/0618_2024-10-16-0946.oao",
    "local_file": "/home/jovyan/work/sse-results/events/2024/gpslogs/20241016/GIB618JEN_618_20241016_094643.oao",
    "size": 970816,
    "start_date": 1729068403000,
    "end_date": 1729087777000,
    "duration": 19374000,
    "distance": 28820597,
    "2s_best": 15608,
    "10s_best": 14977,
    "500m_best": 14128,
    "status": "completed"
  },
  "GIB618JEN_618_20241017_094901.oao": {
    "motion_file": "/logs/2024/10/0618_2024-10-17-0949.oao",
    "local_file": "/home/jovyan/work/sse-results/events/2024/gpslogs/20241017/GIB618JEN_618_20241017_094901.oao",
    "size": 2328484,
    "start_date": 1729154941000,
    "end_date": 1729181487000,
    "duration": 26546000,
    "distance": 69104151,
    "2s_best": 13612,
    "10s_best": 13390,
    "500m_best": 13098,
    "status": "completed"
  },
  "GIB618JEN_618_20241018_095202.oao": {
    "motion_file": "/logs/2024/10/0618_2024-10-18-0952.oao",
    "local_file": "/home/jovyan/work/sse-results/events/2024/gpslogs/20241018/GIB618JEN_618_20241018_095202.oao",
    "size": 1995996,
    "start_date": 1729241522000,
    "end_date": 1729267253000,
    "duration": 25731000,
    "distance": 69619323,
    "2s_best": 16031,
    "10s_best": 15624,
    "500m_best": 15272,
    "status": "completed"
  },
  "ROG618KAT_618_20241012_104131.oao": {
    "motion_file": "/logs/2024/10/0618_2024-10-12-1041.oao",
    "local_file": "/home/jovyan/work/sse-results/events/2025/gpslogs/20241012/ROG618KAT_618_20241012_104131.oao",
    "size": 1248236,
    "start_date": 1728726091000,
    "end_date": 1728751119000,
    "duration": 25028000,
    "distance": 48372930,
    "2s_best": 15624,
    "10s_best": 15431,
    "500m_best": 15056,
    "status": "completed"
  },
  "ROG618KAT_618_20241014_095132.oao": {
    "motion_file": "/logs/2024/10/0618_2024-10-14-0951.oao",
    "local_file": "/home/jovyan/work/sse-results/events/2025/gpslogs/20241014/ROG618KAT_618_20241014_095132.oao",
    "size": 1835524,
    "start_date": 1728895892000,
    "end_date": 1728915557000,
    "duration": 19665000,
    "distance": 58255030,
    "2s_best": 13432,
    "10s_best": 13204,
    "500m_best": 12989,
    "status": "completed"
  },
  "ROG618KAT_618_20241015_094836.oao": {
    "motion_file": "/logs/2024/10/0618_2024-10-15-0948.oao",
    "local_file": "/home/jovyan/work/sse-results/events/2025/gpslogs/20241015/ROG618KAT_618_20241015_094836.oao",
    "size": 1907232,
    "start_date": 1728982116000,
    "end_date": 1729008863000,
    "duration": 26747000,
    "distance": 78167856,
    "2s_best": 15596,
    "10s_best": 15230,
    "500m_best": 15024,
    "status": "completed"
  },
  "ROG618KAT_618_20241016_094643.oao": {
    "motion_file": "/logs/2024/10/0618_2024-10-16-0946.oao",
    "local_file": "/home/jovyan/work/sse-results/events/2025/gpslogs/20241016/ROG618KAT_618_20241016_094643.oao",
    "size": 970816,
    "start_date": 1729068403000,
    "end_date": 1729087777000,
    "duration": 19374000,
    "distance": 28820597,
    "2s_best": 15608,
    "10s_best": 14977,
    "500m_best": 14128,
    "status": "completed"
  },
  "ROG618KAT_618_20241017_094901.oao": {
    "motion_file": "/logs/2024/10/0618_2024-10-17-0949.oao",
    "local_file": "/home/jovyan/work/sse-results/events/2025/gpslogs/20241017/ROG618KAT_618_20241017_094901.oao",
    "size": 2328484,
    "start_date": 1729154941000,
    "end_date": 1729181487000,
    "duration": 26546000,
    "distance": 69104151,
    "2s_best": 13612,
    "10s_best": 13390,
    "500m_best": 13098,
    "status": "completed"
  },
  "ROG618KAT_618_20241018_095202.oao": {
    "motion_file": "/logs/2024/10/0618_2024-10-18-0952.oao",
    "local_file": "/home/jovyan/work/sse-results/events/2025/gpslogs/20241018/ROG618KAT_618_20241018_095202.oao",
    "size": 1995996,
    "start_date": 1729241522000,
    "end_date": 1729267253000,
    "duration": 25731000,
    "distance": 69619323,
    "2s_best": 16031,
    "10s_best": 15624,
    "500m_best": 15272,
    "status": "completed"
  },
  "ROG618KAT_618_20251012_094909.oao": {
    "motion_file": "/logs/2025/10/0618_2025-10-12-0949.oao",
    "local_file": "/home/jovyan/work/sse-results/events/2025/gpslogs/20251012/ROG618KAT_618_20251012_094909.oao",
    "size": 547328,
    "start_date": 1760258949000,
    "end_date": 1760284305000,
    "duration": 25356000,
    "distance": 16767925,
    "2s_best": 9206,
    "10s_best": 9024,
    "500m_best": 8696,
    "status": "completed"
  },
  "ROG618KAT_618_20251013_095405.oao": {
    "motion_file": "/logs/2025/10/0618_2025-10-13-0954.oao",
    "local_file": "/home/jovyan/work/sse-results/events/2025/gpslogs/20251013/ROG618KAT_618_20251013_095405.oao",
    "size": 1106900,
    "start_date": 1760345645000,
    "end_date": 1760366633000,
    "duration": 20988000,
    "distance": 29756096,
    "2s_best": 10227,
    "10s_best": 10070,
    "500m_best": 9381,
    "status": "completed"
  },
  "ROG618KAT_618_20251014_094625.oao": {
    "motion_file": "/logs/2025/10/0618_2025-10-14-0946.oao",
    "local_file": "/home/jovyan/work/sse-results/events/2025/gpslogs/20251014/ROG618KAT_618_20251014_094625.oao",
    "size": 809668,
    "start_date": 1760431585000,
    "end_date": 1760440837000,
    "duration": 9252000,
    "distance": 19173591,
    "2s_best": 10746,
    "10s_best": 9966,
    "500m_best": 9280,
    "status": "completed"
  },
  "ROG618KAT_618_20251015_094601.oao": {
    "motion_file": "/logs/2025/10/0618_2025-10-15-0946.oao",
    "local_file": "/home/jovyan/work/sse-results/events/2025/gpslogs/20251015/ROG618KAT_618_20251015_094601.oao",
    "size": 1278136,
    "start_date": 1760517961000,
    "end_date": 1760541105000,
    "duration": 23144000,
    "distance": 32976623,
    "2s_best": 10080,
    "10s_best": 9715,
    "500m_best": 9369,
    "status": "completed"
  },
  "ROG618KAT_618_20251016_094139.oao": {
    "motion_file": "/logs/2025/10/0618_2025-10-16-0941.oao",
    "local_file": "/home/jovyan/work/sse-results/events/2025/gpslogs/20251016/ROG618KAT_618_20251016_094139.oao",
    "size": 435320,
    "start_date": 1760604099000,
    "end_date": 1760613867000,
    "duration": 9768000,
    "distance": 11566469,
    "2s_best": 9239,
    "10s_best": 9150,
    "500m_best": 8477,
    "status": "completed"
  }
}