{
  "CUN123BOB_648_20221015_110338.oao": {
    "motion_file": "/logs/2022/10/0648_2022-10-15-1103.oao",
    "local_file": "/home/jovyan/work/sse-results/events/2022/gpslogs/20221015/CUN123BOB_648_20221015_110338.oao",
    "size": 347024,
    "start_date": 1665828218000,
    "end_date": 1665851946000,
    "duration": 23728000,
    "distance": 17099673,
    "2s_best": 18442,
    "10s_best": 18061,
    "500m_best": 17299,
    "status": "completed"
  },
  "LIL648MAT_648_20231007_103656.oao": {
    "motion_file": "/logs/2023/10/0648_2023-10-07-1036.oao",
    "local_file": "/home/jovyan/work/sse-results/events/2023/gpslogs/20231007/LIL648MAT_648_20231007_103656.oao",
    "size": 10064,
    "start_date": 1696671416000,
    "end_date": 1696682598000,
    "duration": 11182000,
    "distance": 3924584,
    "2s_best": 3347,
    "10s_best": 2753,
    "500m_best": 1574,
    "status": "completed"
  },
  "LIL648MAT_648_20231010_094418.oao": {
    "motion_file": "/logs/2023/10/0648_2023-10-10-0944.oao",
    "local_file": "/home/jovyan/work/sse-results/events/2023/gpslogs/20231010/LIL648MAT_648_20231010_094418.oao",
    "size": 334076,
    "start_date": 1696927458000,
    "end_date": 1696949436000,
    "duration": 21978000,
    "distance": 15070950,
    "2s_best": 12324,
    "10s_best": 12093,
    "500m_best": 11660,
    "status": "completed"
  },
  "LIL648MAT_648_20231011_095419.oao": {
    "motion_file": "/logs/2023/10/0648_2023-10-11-0954.oao",
    "local_file": "/home/jovyan/work/sse-results/events/2023/gpslogs/20231011/LIL648MAT_648_20231011_095419.oao",
    "size": 968268,
    "start_date": 1697014459000,
    "end_date": 1697033388000,
    "duration": 18929000,
    "distance": 35183161,
    "2s_best": 13246,
    "10s_best": 13065,
    "500m_best": 12635,
    "status": "completed"
  },
  "LIL648MAT_648_20231013_084048.oao": {
    "motion_file": "/logs/2023/10/0648_2023-10-13-0840.oao",
    "local_file": "/home/jovyan/work/sse-results/events/2023/gpslogs/20231013/LIL648MAT_648_20231013_084048.oao",
    "size": 1514944,
    "start_date": 1697182848000,
    "end_date": 1697209994000,
    "duration": 27146000,
    "distance": 56479940,
    "2s_best": 16008,
    "10s_best": 15556,
    "500m_best": 14970,
    "status": "completed"
  },
  "MAR648EDD_648_20241012_105141.oao": {
    "motion_file": "/logs/2024/10/0648_2024-10-12-1051.oao",
    "local_file": "/home/jovyan/work/sse-results/events/2024/gpslogs/20241012/MAR648EDD_648_20241012_105141.oao",
    "size": 5592,
    "start_date": 1728726701000,
    "end_date": 1728749143000,
    "duration": 22442000,
    "distance": 515216,
    "2s_best": 1967,
    "10s_best": 1636,
    "500m_best": 0,
    "status": "skipped"
  },
  "MAR648EDD_648_20241015_141807.oao": {
    "motion_file": "/logs/2024/10/0648_2024-10-15-1418.oao",
    "local_file": "/home/jovyan/work/sse-results/events/2024/gpslogs/20241015/MAR648EDD_648_20241015_141807.oao",
    "size": 873836,
    "start_date": 1728998287000,
    "end_date": 1729007265000,
    "duration": 8978000,
    "distance": 17532499,
    "2s_best": 9083,
    "10s_best": 8728,
    "500m_best": 8285,
    "status": "completed"
  },
  "MAR648EDD_648_20241016_110819.oao": {
    "motion_file": "/logs/2024/10/0648_2024-10-16-1108.oao",
    "local_file": "/home/jovyan/work/sse-results/events/2024/gpslogs/20241016/MAR648EDD_648_20241016_110819.oao",
    "size": 1536,
    "start_date": 1729073299000,
    "end_date": 1729083139000,
    "duration": 9840000,
    "distance": 142310,
    "2s_best": 1147,
    "10s_best": 0,
    "500m_best": 0,
    "status": "skipped"
  },
  "MAR648EDD_648_20241017_102909.oao": {
    "motion_file": "/logs/2024/10/0648_2024-10-17-1029.oao",
    "local_file": "/home/jovyan/work/sse-results/events/2024/gpslogs/20241017/MAR648EDD_648_20241017_102909.oao",
    "size": 187332,
    "start_date": 1729157349000,
    "end_date": 1729179677000,
    "duration": 22328000,
    "distance": 2319298,
    "2s_best": 3600,
    "10s_best": 2886,
    "500m_best": 1002,
    "status": "completed"
  },
  "MAR648EDD_648_20241018_120847.oao": {
    "motion_file": "/logs/2024/10/0648_2024-10-18-1208.oao",
    "local_file": "/home/jovyan/work/sse-results/events/2024/gpslogs/20241018/MAR648EDD_648_20241018_120847.oao",
    "size": 421436,
    "start_date": 1729249727000,
    "end_date": 1729264459000,
    "duration": 14732000,
    "distance": 7735729,
    "2s_best": 13417,
    "10s_best": 13289,
    "500m_best": 11425,
    "status": "completed"
  },
  "WIL648DAV_648_20241012_105141.oao": {
    "motion_file": "/logs/2024/10/0648_2024-10-12-1051.oao",
    "local_file": "/home/jovyan/work/sse-results/events/2025/gpslogs/20241012/WIL648DAV_648_20241012_105141.oao",
    "size": 5592,
    "start_date": 1728726701000,
    "end_date": 1728749143000,
    "duration": 22442000,
    "distance": 515216,
    "2s_best": 1967,
    "10s_best": 1636,
    "500m_best": 0,
    "status": "skipped"
  },
  "WIL648DAV_648_20241015_141807.oao": {
    "motion_file": "/logs/2024/10/0648_2024-10-15-1418.oao",
    "local_file": "/home/jovyan/work/sse-results/events/2025/gpslogs/20241015/WIL648DAV_648_20241015_141807.oao",
    "size": 873836,
    "start_date": 1728998287000,
    "end_date": 1729007265000,
    "duration": 8978000,
    "distance": 17532499,
    "2s_best": 9083,
    "10s_best": 8728,
    "500m_best": 8285,
    "status": "completed"
  },
  "WIL648DAV_648_20241016_110819.oao": {
    "motion_file": "/logs/2024/10/0648_2024-10-16-1108.oao",
    "local_file": "/home/jovyan/work/sse-results/events/2025/gpslogs/20241016/WIL648DAV_648_20241016_110819.oao",
    "size": 1536,
    "start_date": 1729073299000,
    "end_date": 1729083139000,
    "duration": 9840000,
    "distance": 142310,
    "2s_best": 1147,
    "10s_best": 0,
    "500m_best": 0,
    "status": "skipped"
  },
  "WIL648DAV_648_20241017_102909.oao": {
    "motion_file": "/logs/2024/10/0648_2024-10-17-1029.oao",
    "local_file": "/home/jovyan/work/sse-results/events/2025/gpslogs/20241017/WIL648DAV_648_20241017_102909.oao",
    "size": 187332,
    "start_date": 1729157349000,
    "end_date": 1729179677000,
    "duration": 22328000,
    "distance": 2319298,
    "2s_best": 3600,
    "10s_best": 2886,
    "500m_best": 1002,
    "status": "completed"
  },
  "WIL648DAV_648_20241018_120847.oao": {
    "motion_file": "/logs/2024/10/0648_2024-10-18-1208.oao",
    "local_file": "/home/jovyan/work/sse-results/events/2025/gpslogs/20241018/WIL648DAV_648_20241018_120847.oao",
    "size": 421436,
    "start_date": 1729249727000,
    "end_date": 1729264459000,
    "duration": 14732000,
    "distance": 7735729,
    "2s_best": 13417,
    "10s_best": 13289,
    "500m_best": 11425,
    "status": "completed"
  },
  "WIL648DAV_648_20251011_105701.oao": {
    "motion_file": "/logs/2025/10/0648_2025-10-11-1057.oao",
    "local_file": "/home/jovyan/work/sse-results/events/2025/gpslogs/20251011/WIL648DAV_648_20251011_105701.oao",
    "size": 74804,
    "start_date": 1760176621000,
    "end_date": 1760191185000,
    "duration": 14564000,
    "distance": 3978116,
    "2s_best": 19464,
    "10s_best": 19047,
    "500m_best": 18388,
    "status": "completed"
  },
  "WIL648DAV_648_20251012_094637.oao": {
    "motion_file": "/logs/2025/10/0648_2025-10-12-0946.oao",
    "local_file": "/home/jovyan/work/sse-results/events/2025/gpslogs/20251012/WIL648DAV_648_20251012_094637.oao",
    "size": 1002848,
    "start_date": 1760258797000,
    "end_date": 1760284473000,
    "duration": 25676000,
    "distance": 26563179,
    "2s_best": 22517,
    "10s_best": 22412,
    "500m_best": 21892,
    "status": "completed"
  },
  "WIL648DAV_648_20251013_103313.oao": {
    "motion_file": "/logs/2025/10/0648_2025-10-13-1033.oao",
    "local_file": "/home/jovyan/work/sse-results/events/2025/gpslogs/20251013/WIL648DAV_648_20251013_103313.oao",
    "size": 859432,
    "start_date": 1760347993000,
    "end_date": 1760366669000,
    "duration": 18676000,
    "distance": 20369365,
    "2s_best": 20338,
    "10s_best": 19999,
    "500m_best": 19903,
    "status": "completed"
  },
  "WIL648DAV_648_20251014_095250.oao": {
    "motion_file": "/logs/2025/10/0648_2025-10-14-0952.oao",
    "local_file": "/home/jovyan/work/sse-results/events/2025/gpslogs/20251014/WIL648DAV_648_20251014_095250.oao",
    "size": 192584,
    "start_date": 1760431970000,
    "end_date": 1760452757000,
    "duration": 20787000,
    "distance": 3011975,
    "2s_best": 22175,
    "10s_best": 21135,
    "500m_best": 19771,
    "status": "completed"
  },
  "WIL648DAV_648_20251015_094709.oao": {
    "motion_file": "/logs/2025/10/0648_2025-10-15-0947.oao",
    "local_file": "/home/jovyan/work/sse-results/events/2025/gpslogs/20251015/WIL648DAV_648_20251015_094709.oao",
    "size": 958336,
    "start_date": 1760518029000,
    "end_date": 1760539609000,
    "duration": 21580000,
    "distance": 26751505,
    "2s_best": 20455,
    "10s_best": 20342,
    "500m_best": 20105,
    "status": "completed"
  },
  "WIL648DAV_648_20251016_094439.oao": {
    "motion_file": "/logs/2025/10/0648_2025-10-16-0944.oao",
    "local_file": "/home/jovyan/work/sse-results/events/2025/gpslogs/20251016/WIL648DAV_648_20251016_094439.oao",
    "size": 160864,
    "start_date": 1760604279000,
    "end_date": 1760616653000,
    "duration": 12374000,
    "distance": 5637255,
    "2s_best": 19309,
    "10s_best": 19212,
    "500m_best": 19093,
    "status": "completed"
  },
  "WIL648DAV_648_20251017_092901.oao": {
    "motion_file": "/logs/2025/10/0648_2025-10-17-0929.oao",
    "local_file": "/home/jovyan/work/sse-results/events/2025/gpslogs/20251017/WIL648DAV_648_20251017_092901.oao",
    "size": 93680,
    "start_date": 1760689741000,
    "end_date": 1760715371000,
    "duration": 25630000,
    "distance": 4003806,
    "2s_best": 19988,
    "10s_best": 19859,
    "500m_best": 19743,
    "status": "completed"
  }
}