{
  "logs": [
    {
      "file": "/logs/2022/09/0656_2022-09-21-2120.oao",
      "size": 999936,
      "timezone": 120,
      "mode": 0,
      "start_date": 1663788020000,
      "end_date": 1663791860000,
      "duration": 3840000,
      "distance": 25439,
      "2s_best": 1056,
      "10s_best": 0,
      "500m_best": 0,
      "1852m_best": 0,
      "a500m_best": 0,
      "1h_best": 0,
      "spot": "",
      "wind": "",
      "board": "",
      "sail": "",
      "fin": ""
    },
    {
      "file": "/logs/2022/10/0656_2022-10-05-2002.oao",
      "size": 1336896,
      "timezone": 120,
      "mode": 0,
      "start_date": 1664992972000,
      "end_date": 1664998108000,
      "duration": 5136000,
      "distance": 34533,
      "2s_best": 0,
      "10s_best": 0,
      "500m_best": 0,
      "1852m_best": 0,
      "a500m_best": 0,
      "1h_best": 0,
      "spot": "",
      "wind": "",
      "board": "",
      "sail": "",
      "fin": ""
    },
    {
      "file": "/logs/2022/10/0656_2022-10-05-2142.oao",
      "size": 1536,
      "timezone": 120,
      "mode": 0,
      "start_date": 1664998944000,
      "end_date": 1664998944000,
      "duration": 0,
      "distance": 0,
      "2s_best": 0,
      "10s_best": 0,
      "500m_best": 0,
      "1852m_best": 0,
      "a500m_best": 0,
      "1h_best": 0,
      "spot": "",
      "wind": "",
      "board": "",
      "sail": "",
      "fin": ""
    },
    {
      "file": "/logs/2022/10/0656_2022-10-05-2137.oao",
      "size": 979136,
      "timezone": 60,
      "mode": 0,
      "start_date": 1665002260000,
      "end_date": 1665006020000,
      "duration": 3760000,
      "distance": 2648,
      "2s_best": 1132,
      "10s_best": 0,
      "500m_best": 0,
      "1852m_best": 0,
      "a500m_best": 0,
      "1h_best": 0,
      "spot": "",
      "wind": "",
      "board": "",
      "sail": "",
      "fin": ""
    },
    {
      "file": "/logs/2022/10/0656_2022-10-05-2242.oao",
      "size": 1536,
      "timezone": 60,
      "mode": 0,
      "start_date": 1665006156000,
      "end_date": 1665006156000,
      "duration": 0,
      "distance": 0,
      "2s_best": 0,
      "10s_best": 0,
      "500m_best": 0,
      "1852m_best": 0,
      "a500m_best": 0,
      "1h_best": 0,
      "spot": "",
      "wind": "",
      "board": "",
      "sail": "",
      "fin": ""
    },
    {
      "file": "/logs/2022/10/0656_2022-10-08-0902.oao",
      "size": 3907776,
      "timezone": 60,
      "mode": 0,
      "start_date": 1665216122000,
      "end_date": 1665231146000,
      "duration": 15024000,
      "distance": 8072805,
      "2s_best": 1930,
      "10s_best": 1849,
      "500m_best": 1740,
      "1852m_best": 1681,
      "a500m_best": 0,
      "1h_best": 1491,
      "spot": "",
      "wind": "",
      "board": "",
      "sail": "",
      "fin": ""
    },
    {
      "file": "/logs/2022/10/0656_2022-10-08-1606.oao",
      "size": 1536,
      "timezone": 60,
      "mode": 0,
      "start_date": 1665241578000,
      "end_date": 1665241578000,
      "duration": 0,
      "distance": 0,
      "2s_best": 0,
      "10s_best": 0,
      "500m_best": 0,
      "1852m_best": 0,
      "a500m_best": 0,
      "1h_best": 0,
      "spot": "",
      "wind": "",
      "board": "",
      "sail": "",
      "fin": ""
    },
    {
      "file": "/logs/2022/10/0656_2022-10-09-1104.oao",
      "size": 522368,
      "timezone": 60,
      "mode": 0,
      "start_date": 1665309858000,
      "end_date": 1665322096000,
      "duration": 12238000,
      "distance": 21431254,
      "2s_best": 10348,
      "10s_best": 9965,
      "500m_best": 9148,
      "1852m_best": 6554,
      "a500m_best": 6970,
      "1h_best": 0,
      "spot": "",
      "wind": "",
      "board": "",
      "sail": "",
      "fin": ""
    },
    {
      "file": "/logs/2022/10/0656_2022-10-09-2152.oao",
      "size": 1536,
      "timezone": 60,
      "mode": 0,
      "start_date": 1665348744000,
      "end_date": 1665349544000,
      "duration": 800000,
      "distance": 60,
      "2s_best": 0,
      "10s_best": 0,
      "500m_best": 0,
      "1852m_best": 0,
      "a500m_best": 0,
      "1h_best": 0,
      "spot": "",
      "wind": "",
      "board": "",
      "sail": "",
      "fin": ""
    },
    {
      "file": "/logs/2022/10/0656_2022-10-09-2205.oao",
      "size": 1536,
      "timezone": 60,
      "mode": 0,
      "start_date": 1665349544000,
      "end_date": 1665351346000,
      "duration": 1802000,
      "distance": 566,
      "2s_best": 0,
      "10s_best": 0,
      "500m_best": 0,
      "1852m_best": 0,
      "a500m_best": 0,
      "1h_best": 0,
      "spot": "",
      "wind": "",
      "board": "",
      "sail": "",
      "fin": ""
    },
    {
      "file": "/logs/2022/10/0656_2022-10-09-2235.oao",
      "size": 1536,
      "timezone": 60,
      "mode": 0,
      "start_date": 1665351346000,
      "end_date": 1665351990000,
      "duration": 644000,
      "distance": 630,
      "2s_best": 0,
      "10s_best": 0,
      "500m_best": 0,
      "1852m_best": 0,
      "a500m_best": 0,
      "1h_best": 0,
      "spot": "",
      "wind": "",
      "board": "",
      "sail": "",
      "fin": ""
    },
    {
      "file": "/logs/2022/10/0656_2022-10-09-2250.oao",
      "size": 1536,
      "timezone": 60,
      "mode": 0,
      "start_date": 1665352218000,
      "end_date": 1665352880000,
      "duration": 662000,
      "distance": 692,
      "2s_best": 0,
      "10s_best": 0,
      "500m_best": 0,
      "1852m_best": 0,
      "a500m_best": 0,
      "1h_best": 0,
      "spot": "",
      "wind": "",
      "board": "",
      "sail": "",
      "fin": ""
    },
    {
      "file": "/logs/2022/10/0656_2022-10-09-2308.oao",
      "size": 1536,
      "timezone": 60,
      "mode": 0,
      "start_date": 1665353332000,
      "end_date": 1665353332000,
      "duration": 0,
      "distance": 0,
      "2s_best": 0,
      "10s_best": 0,
      "500m_best": 0,
      "1852m_best": 0,
      "a500m_best": 0,
      "1h_best": 0,
      "spot": "",
      "wind": "",
      "board": "",
      "sail": "",
      "fin": ""
    },
    {
      "file": "/logs/2022/10/0656_2022-10-10-1832.oao",
      "size": 1536,
      "timezone": 60,
      "mode": 0,
      "start_date": 1665423178000,
      "end_date": 1665423178000,
      "duration": 0,
      "distance": 0,
      "2s_best": 0,
      "10s_best": 0,
      "500m_best": 0,
      "1852m_best": 0,
      "a500m_best": 0,
      "1h_best": 0,
      "spot": "",
      "wind": "",
      "board": "",
      "sail": "",
      "fin": ""
    },
    {
      "file": "/logs/2022/10/0656_2022-10-15-1058.oao",
      "size": 1704120,
      "timezone": 60,
      "mode": 0,
      "start_date": 1665827898000,
      "end_date": 1665852160000,
      "duration": 24262000,
      "distance": 58032334,
      "2s_best": 22887,
      "10s_best": 21935,
      "500m_best": 21408,
      "1852m_best": 18576,
      "a500m_best": 7510,
      "1h_best": 4468,
      "spot": "",
      "wind": "",
      "board": "",
      "sail": "",
      "fin": ""
    }
  ]
}