{
  "COL871ANN_871_20231011_105828.oao": {
    "motion_file": "/logs/2023/10/0871_2023-10-11-1058.oao",
    "local_file": "/home/jovyan/work/sse-results/events/2023/gpslogs/20231011/COL871ANN_871_20231011_105828.oao",
    "size": 2566384,
    "start_date": 1697018308000,
    "end_date": 1697037526000,
    "duration": 19218000,
    "distance": 73798876,
    "2s_best": 13235,
    "10s_best": 13071,
    "500m_best": 12831,
    "status": "completed"
  },
  "COL871ANN_871_20231013_095210.oao": {
    "motion_file": "/logs/2023/10/0871_2023-10-13-0952.oao",
    "local_file": "/home/jovyan/work/sse-results/events/2023/gpslogs/20231013/COL871ANN_871_20231013_095210.oao",
    "size": 2406640,
    "start_date": 1697187130000,
    "end_date": 1697211076000,
    "duration": 23946000,
    "distance": 74184630,
    "2s_best": 14088,
    "10s_best": 13765,
    "500m_best": 13540,
    "status": "completed"
  }
}