{
  "logs": [
    {
      "file": "/logs/2023/10/0607_2023-10-07-1025.oao",
      "size": 852308,
      "timezone": 60,
      "mode": 0,
      "start_date": 1696670702000,
      "end_date": 1696690936000,
      "duration": 20234000,
      "distance": 38327541,
      "2s_best": 13663,
      "10s_best": 13421,
      "500m_best": 13094,
      "1852m_best": 10396,
      "a500m_best": 9521,
      "1h_best": 3996,
      "spot": "",
      "wind": "",
      "board": "",
      "sail": "",
      "fin": ""
    },
    {
      "file": "/logs/2023/10/0607_2023-10-10-0947.oao",
      "size": 895052,
      "timezone": 60,
      "mode": 0,
      "start_date": 1696927660000,
      "end_date": 1696951750000,
      "duration": 24090000,
      "distance": 41621639,
      "2s_best": 14923,
      "10s_best": 14557,
      "500m_best": 14307,
      "1852m_best": 11406,
      "a500m_best": 9634,
      "1h_best": 6127,
      "spot": "",
      "wind": "",
      "board": "",
      "sail": "",
      "fin": ""
    },
    {
      "file": "/logs/2023/10/0607_2023-10-11-0950.oao",
      "size": 2483860,
      "timezone": 60,
      "mode": 0,
      "start_date": 1697014254000,
      "end_date": 1697037470000,
      "duration": 23216000,
      "distance": 91176308,
      "2s_best": 15067,
      "10s_best": 14899,
      "500m_best": 14281,
      "1852m_best": 11401,
      "a500m_best": 8719,
      "1h_best": 5431,
      "spot": "",
      "wind": "",
      "board": "",
      "sail": "",
      "fin": ""
    },
    {
      "file": "/logs/2023/10/0607_2023-10-12-1049.oao",
      "size": 1263524,
      "timezone": 60,
      "mode": 0,
      "start_date": 1697104148000,
      "end_date": 1697123890000,
      "duration": 19742000,
      "distance": 53955339,
      "2s_best": 15704,
      "10s_best": 15397,
      "500m_best": 15192,
      "1852m_best": 11879,
      "a500m_best": 8885,
      "1h_best": 4826,
      "spot": "",
      "wind": "",
      "board": "",
      "sail": "",
      "fin": ""
    },
    {
      "file": "/logs/2023/10/0607_2023-10-13-0858.oao",
      "size": 1236744,
      "timezone": 60,
      "mode": 0,
      "start_date": 1697183916000,
      "end_date": 1697209928000,
      "duration": 26012000,
      "distance": 51430555,
      "2s_best": 18416,
      "10s_best": 18195,
      "500m_best": 17613,
      "1852m_best": 10844,
      "a500m_best": 10352,
      "1h_best": 3357,
      "spot": "",
      "wind": "",
      "board": "",
      "sail": "",
      "fin": ""
    },
    {
      "file": "/logs/2024/04/0607_2024-04-22-1303.oao",
      "size": 86452,
      "timezone": 60,
      "mode": 0,
      "start_date": 1713787382000,
      "end_date": 1713794148000,
      "duration": 6766000,
      "distance": 8107430,
      "2s_best": 20165,
      "10s_best": 19758,
      "500m_best": 19338,
      "1852m_best": 2491,
      "a500m_best": 0,
      "1h_best": 1297,
      "spot": "",
      "wind": "",
      "board": "",
      "sail": "",
      "fin": ""
    },
    {
      "file": "/logs/2024/04/0607_2024-04-23-0956.oao",
      "size": 422216,
      "timezone": 60,
      "mode": 0,
      "start_date": 1713862596000,
      "end_date": 1713883742000,
      "duration": 21146000,
      "distance": 27663319,
      "2s_best": 25895,
      "10s_best": 25628,
      "500m_best": 25176,
      "1852m_best": 16451,
      "a500m_best": 7867,
      "1h_best": 3074,
      "spot": "",
      "wind": "",
      "board": "",
      "sail": "",
      "fin": ""
    },
    {
      "file": "/logs/2024/04/0607_2024-04-24-1007.oao",
      "size": 198200,
      "timezone": 60,
      "mode": 0,
      "start_date": 1713949640000,
      "end_date": 1713970216000,
      "duration": 20576000,
      "distance": 24805881,
      "2s_best": 21664,
      "10s_best": 21319,
      "500m_best": 20796,
      "1852m_best": 3043,
      "a500m_best": 0,
      "1h_best": 2171,
      "spot": "",
      "wind": "",
      "board": "",
      "sail": "",
      "fin": ""
    },
    {
      "file": "/logs/2024/04/0607_2024-04-27-1150.oao",
      "size": 1703964,
      "timezone": 60,
      "mode": 0,
      "start_date": 1714215024000,
      "end_date": 1714226408000,
      "duration": 11384000,
      "distance": 75475746,
      "2s_best": 18042,
      "10s_best": 17239,
      "500m_best": 15664,
      "1852m_best": 13070,
      "a500m_best": 11022,
      "1h_best": 7789,
      "spot": "",
      "wind": "",
      "board": "",
      "sail": "",
      "fin": ""
    },
    {
      "file": "/logs/2024/05/0607_2024-05-02-1035.oao",
      "size": 212812,
      "timezone": 60,
      "mode": 0,
      "start_date": 1714642508000,
      "end_date": 1714653492000,
      "duration": 10984000,
      "distance": 10384662,
      "2s_best": 17671,
      "10s_best": 17229,
      "500m_best": 16561,
      "1852m_best": 6132,
      "a500m_best": 0,
      "1h_best": 0,
      "spot": "",
      "wind": "",
      "board": "",
      "sail": "",
      "fin": ""
    },
    {
      "file": "/logs/2024/05/0607_2024-05-06-1015.oao",
      "size": 1343136,
      "timezone": 60,
      "mode": 0,
      "start_date": 1714986910000,
      "end_date": 1714996402000,
      "duration": 9492000,
      "distance": 55028131,
      "2s_best": 14508,
      "10s_best": 14253,
      "500m_best": 13246,
      "1852m_best": 12766,
      "a500m_best": 9290,
      "1h_best": 7292,
      "spot": "",
      "wind": "",
      "board": "",
      "sail": "",
      "fin": ""
    },
    {
      "file": "/logs/2024/05/0607_2024-05-06-1548.oao",
      "size": 176412,
      "timezone": 60,
      "mode": 0,
      "start_date": 1715006930000,
      "end_date": 1715011684000,
      "duration": 4754000,
      "distance": 10074999,
      "2s_best": 12954,
      "10s_best": 12452,
      "500m_best": 11575,
      "1852m_best": 7140,
      "a500m_best": 4828,
      "1h_best": 2651,
      "spot": "",
      "wind": "",
      "board": "",
      "sail": "",
      "fin": ""
    },
    {
      "file": "/logs/2024/05/0607_2024-05-07-1126.oao",
      "size": 1947688,
      "timezone": 60,
      "mode": 0,
      "start_date": 1715077616000,
      "end_date": 1715103260000,
      "duration": 25644000,
      "distance": 94260039,
      "2s_best": 15499,
      "10s_best": 15245,
      "500m_best": 14798,
      "1852m_best": 13657,
      "a500m_best": 9534,
      "1h_best": 9074,
      "spot": "",
      "wind": "",
      "board": "",
      "sail": "",
      "fin": ""
    },
    {
      "file": "/logs/2024/05/0607_2024-05-08-1624.oao",
      "size": 958284,
      "timezone": 60,
      "mode": 0,
      "start_date": 1715181898000,
      "end_date": 1715188726000,
      "duration": 6828000,
      "distance": 41926937,
      "2s_best": 15297,
      "10s_best": 15177,
      "500m_best": 14329,
      "1852m_best": 13402,
      "a500m_best": 7367,
      "1h_best": 8794,
      "spot": "",
      "wind": "",
      "board": "",
      "sail": "",
      "fin": ""
    },
    {
      "file": "/logs/2024/05/0607_2024-05-15-1541.oao",
      "size": 1199096,
      "timezone": 60,
      "mode": 0,
      "start_date": 1715784070000,
      "end_date": 1715794468000,
      "duration": 10398000,
      "distance": 50451031,
      "2s_best": 13719,
      "10s_best": 13446,
      "500m_best": 12838,
      "1852m_best": 12081,
      "a500m_best": 9488,
      "1h_best": 7014,
      "spot": "",
      "wind": "",
      "board": "",
      "sail": "",
      "fin": ""
    },
    {
      "file": "/logs/2024/05/0607_2024-05-20-1506.oao",
      "size": 832600,
      "timezone": 60,
      "mode": 0,
      "start_date": 1716213970000,
      "end_date": 1716224062000,
      "duration": 10092000,
      "distance": 38142010,
      "2s_best": 14237,
      "10s_best": 14058,
      "500m_best": 13241,
      "1852m_best": 10744,
      "a500m_best": 9218,
      "1h_best": 5485,
      "spot": "",
      "wind": "",
      "board": "",
      "sail": "",
      "fin": ""
    },
    {
      "file": "/logs/2024/05/0607_2024-05-25-1726.oao",
      "size": 8504,
      "timezone": 60,
      "mode": 0,
      "start_date": 1716654362000,
      "end_date": 1716656308000,
      "duration": 1946000,
      "distance": 2671466,
      "2s_best": 3595,
      "10s_best": 2893,
      "500m_best": 2148,
      "1852m_best": 1695,
      "a500m_best": 0,
      "1h_best": 0,
      "spot": "",
      "wind": "",
      "board": "",
      "sail": "",
      "fin": ""
    },
    {
      "file": "/logs/2024/05/0607_2024-05-26-1228.oao",
      "size": 1521860,
      "timezone": 60,
      "mode": 0,
      "start_date": 1716722910000,
      "end_date": 1716738840000,
      "duration": 15930000,
      "distance": 63544324,
      "2s_best": 14981,
      "10s_best": 14676,
      "500m_best": 14053,
      "1852m_best": 12110,
      "a500m_best": 10205,
      "1h_best": 7570,
      "spot": "",
      "wind": "",
      "board": "",
      "sail": "",
      "fin": ""
    },
    {
      "file": "/logs/2024/05/0607_2024-05-28-1511.oao",
      "size": 214216,
      "timezone": 60,
      "mode": 0,
      "start_date": 1716905460000,
      "end_date": 1716906278000,
      "duration": 818000,
      "distance": 6526437,
      "2s_best": 17866,
      "10s_best": 17346,
      "500m_best": 16314,
      "1852m_best": 12468,
      "a500m_best": 9385,
      "1h_best": 0,
      "spot": "",
      "wind": "",
      "board": "",
      "sail": "",
      "fin": ""
    },
    {
      "file": "/logs/2024/05/0607_2024-05-28-1524.oao",
      "size": 1536,
      "timezone": 60,
      "mode": 0,
      "start_date": 1716906278000,
      "end_date": 1716906278000,
      "duration": 0,
      "distance": 0,
      "2s_best": 0,
      "10s_best": 0,
      "500m_best": 0,
      "1852m_best": 0,
      "a500m_best": 0,
      "1h_best": 0,
      "spot": "",
      "wind": "",
      "board": "",
      "sail": "",
      "fin": ""
    },
    {
      "file": "/logs/2024/05/0607_2024-05-29-1044.oao",
      "size": 573536,
      "timezone": 60,
      "mode": 0,
      "start_date": 1716975892000,
      "end_date": 1716978092000,
      "duration": 2200000,
      "distance": 2301043,
      "2s_best": 1715,
      "10s_best": 1587,
      "500m_best": 1469,
      "1852m_best": 1253,
      "a500m_best": 0,
      "1h_best": 0,
      "spot": "",
      "wind": "",
      "board": "",
      "sail": "",
      "fin": ""
    },
    {
      "file": "/logs/2024/05/0607_2024-05-27-1302.oao",
      "size": 1427376,
      "timezone": 60,
      "mode": 0,
      "start_date": 1716811330000,
      "end_date": 1716816814000,
      "duration": 5484000,
      "distance": 39215262,
      "2s_best": 14904,
      "10s_best": 14637,
      "500m_best": 14454,
      "1852m_best": 12873,
      "a500m_best": 9150,
      "1h_best": 8027,
      "spot": "",
      "wind": "",
      "board": "",
      "sail": "",
      "fin": ""
    },
    {
      "file": "/logs/2024/05/0607_2024-05-27-1722.oao",
      "size": 1647856,
      "timezone": 60,
      "mode": 0,
      "start_date": 1716826936000,
      "end_date": 1716833268000,
      "duration": 6332000,
      "distance": 29909163,
      "2s_best": 14782,
      "10s_best": 14416,
      "500m_best": 13990,
      "1852m_best": 10819,
      "a500m_best": 9729,
      "1h_best": 6246,
      "spot": "",
      "wind": "",
      "board": "",
      "sail": "",
      "fin": ""
    },
    {
      "file": "/logs/2024/05/0607_2024-05-29-1431.oao",
      "size": 2546416,
      "timezone": 60,
      "mode": 0,
      "start_date": 1716989494000,
      "end_date": 1716999282000,
      "duration": 9788000,
      "distance": 66888628,
      "2s_best": 13511,
      "10s_best": 13201,
      "500m_best": 12980,
      "1852m_best": 12224,
      "a500m_best": 9644,
      "1h_best": 9383,
      "spot": "",
      "wind": "",
      "board": "",
      "sail": "",
      "fin": ""
    },
    {
      "file": "/logs/2024/05/0607_2024-05-30-1220.oao",
      "size": 3382576,
      "timezone": 60,
      "mode": 0,
      "start_date": 1717068050000,
      "end_date": 1717081054000,
      "duration": 13004000,
      "distance": 15927273,
      "2s_best": 5618,
      "10s_best": 5357,
      "500m_best": 4466,
      "1852m_best": 3843,
      "a500m_best": 4471,
      "1h_best": 0,
      "spot": "",
      "wind": "",
      "board": "",
      "sail": "",
      "fin": ""
    },
    {
      "file": "/logs/2024/06/0607_2024-06-09-1259.oao",
      "size": 4348216,
      "timezone": 60,
      "mode": 0,
      "start_date": 1717934388000,
      "end_date": 1717951106000,
      "duration": 16718000,
      "distance": 24258906,
      "2s_best": 5405,
      "10s_best": 5173,
      "500m_best": 4734,
      "1852m_best": 3789,
      "a500m_best": 4530,
      "1h_best": 1952,
      "spot": "",
      "wind": "",
      "board": "",
      "sail": "",
      "fin": ""
    },
    {
      "file": "/logs/2024/06/0607_2024-06-10-1101.oao",
      "size": 1116936,
      "timezone": 60,
      "mode": 0,
      "start_date": 1718013670000,
      "end_date": 1718017960000,
      "duration": 4290000,
      "distance": 9065977,
      "2s_best": 14177,
      "10s_best": 13919,
      "500m_best": 11130,
      "1852m_best": 7541,
      "a500m_best": 9806,
      "1h_best": 0,
      "spot": "",
      "wind": "",
      "board": "",
      "sail": "",
      "fin": ""
    },
    {
      "file": "/logs/2024/06/0607_2024-06-10-1216.oao",
      "size": 1378496,
      "timezone": 60,
      "mode": 0,
      "start_date": 1718018168000,
      "end_date": 1718023464000,
      "duration": 5296000,
      "distance": 7284129,
      "2s_best": 13003,
      "10s_best": 12827,
      "500m_best": 11777,
      "1852m_best": 10526,
      "a500m_best": 0,
      "1h_best": 1975,
      "spot": "",
      "wind": "",
      "board": "",
      "sail": "",
      "fin": ""
    },
    {
      "file": "/logs/2024/06/0607_2024-06-11-1617.oao",
      "size": 1672816,
      "timezone": 60,
      "mode": 0,
      "start_date": 1718119058000,
      "end_date": 1718125486000,
      "duration": 6428000,
      "distance": 27382988,
      "2s_best": 13267,
      "10s_best": 13203,
      "500m_best": 12515,
      "1852m_best": 11708,
      "a500m_best": 9001,
      "1h_best": 4976,
      "spot": "",
      "wind": "",
      "board": "",
      "sail": "",
      "fin": ""
    },
    {
      "file": "/logs/2024/06/0607_2024-06-12-1723.oao",
      "size": 1645256,
      "timezone": 60,
      "mode": 0,
      "start_date": 1718209404000,
      "end_date": 1718215726000,
      "duration": 6322000,
      "distance": 28582541,
      "2s_best": 9651,
      "10s_best": 9393,
      "500m_best": 8564,
      "1852m_best": 8031,
      "a500m_best": 8247,
      "1h_best": 4522,
      "spot": "",
      "wind": "",
      "board": "",
      "sail": "",
      "fin": ""
    },
    {
      "file": "/logs/2024/06/0607_2024-06-13-1140.oao",
      "size": 2442988,
      "timezone": 60,
      "mode": 0,
      "start_date": 1718275254000,
      "end_date": 1718284644000,
      "duration": 9390000,
      "distance": 58342810,
      "2s_best": 14420,
      "10s_best": 14227,
      "500m_best": 13997,
      "1852m_best": 11630,
      "a500m_best": 10202,
      "1h_best": 9237,
      "spot": "",
      "wind": "",
      "board": "",
      "sail": "",
      "fin": ""
    },
    {
      "file": "/logs/2024/06/0607_2024-06-14-1237.oao",
      "size": 2017576,
      "timezone": 60,
      "mode": 0,
      "start_date": 1718365074000,
      "end_date": 1718372828000,
      "duration": 7754000,
      "distance": 41951168,
      "2s_best": 15847,
      "10s_best": 15481,
      "500m_best": 14893,
      "1852m_best": 13062,
      "a500m_best": 9161,
      "1h_best": 8590,
      "spot": "",
      "wind": "",
      "board": "",
      "sail": "",
      "fin": ""
    },
    {
      "file": "/logs/2024/06/0607_2024-06-14-1537.oao",
      "size": 1372776,
      "timezone": 60,
      "mode": 0,
      "start_date": 1718375872000,
      "end_date": 1718381146000,
      "duration": 5274000,
      "distance": 27897729,
      "2s_best": 14981,
      "10s_best": 14693,
      "500m_best": 14146,
      "1852m_best": 11335,
      "a500m_best": 10650,
      "1h_best": 7634,
      "spot": "",
      "wind": "",
      "board": "",
      "sail": "",
      "fin": ""
    },
    {
      "file": "/logs/2024/06/0607_2024-06-15-1120.oao",
      "size": 1041536,
      "timezone": 60,
      "mode": 0,
      "start_date": 1718446850000,
      "end_date": 1718450850000,
      "duration": 4000000,
      "distance": 26194669,
      "2s_best": 18398,
      "10s_best": 17909,
      "500m_best": 16277,
      "1852m_best": 11812,
      "a500m_best": 9768,
      "1h_best": 0,
      "spot": "",
      "wind": "",
      "board": "",
      "sail": "",
      "fin": ""
    },
    {
      "file": "/logs/2024/06/0607_2024-06-15-1723.oao",
      "size": 1011376,
      "timezone": 60,
      "mode": 0,
      "start_date": 1718468590000,
      "end_date": 1718472474000,
      "duration": 3884000,
      "distance": 10461955,
      "2s_best": 13605,
      "10s_best": 13339,
      "500m_best": 12367,
      "1852m_best": 6472,
      "a500m_best": 7955,
      "1h_best": 2894,
      "spot": "",
      "wind": "",
      "board": "",
      "sail": "",
      "fin": ""
    },
    {
      "file": "/logs/2024/06/0607_2024-06-16-1433.oao",
      "size": 3629576,
      "timezone": 60,
      "mode": 0,
      "start_date": 1718544798000,
      "end_date": 1718558752000,
      "duration": 13954000,
      "distance": 67284830,
      "2s_best": 14272,
      "10s_best": 14034,
      "500m_best": 13476,
      "1852m_best": 12382,
      "a500m_best": 8679,
      "1h_best": 9166,
      "spot": "",
      "wind": "",
      "board": "",
      "sail": "",
      "fin": ""
    },
    {
      "file": "/logs/2024/06/0607_2024-06-27-1350.oao",
      "size": 4163096,
      "timezone": 60,
      "mode": 0,
      "start_date": 1719492620000,
      "end_date": 1719508626000,
      "duration": 16006000,
      "distance": 78321927,
      "2s_best": 14152,
      "10s_best": 13699,
      "500m_best": 12897,
      "1852m_best": 12364,
      "a500m_best": 10222,
      "1h_best": 8431,
      "spot": "",
      "wind": "",
      "board": "",
      "sail": "",
      "fin": ""
    },
    {
      "file": "/logs/2024/10/0607_2024-10-12-1155.oao",
      "size": 1475580,
      "timezone": 60,
      "mode": 0,
      "start_date": 1728730533000,
      "end_date": 1728751405000,
      "duration": 20872000,
      "distance": 43785264,
      "2s_best": 12045,
      "10s_best": 11558,
      "500m_best": 10419,
      "1852m_best": 8680,
      "a500m_best": 7632,
      "1h_best": 1671,
      "spot": "",
      "wind": "",
      "board": "",
      "sail": "",
      "fin": ""
    },
    {
      "file": "/logs/2024/10/0607_2024-10-14-0945.oao",
      "size": 179948,
      "timezone": 60,
      "mode": 0,
      "start_date": 1728895531000,
      "end_date": 1728916919000,
      "duration": 21388000,
      "distance": 7138113,
      "2s_best": 9262,
      "10s_best": 9110,
      "500m_best": 8959,
      "1852m_best": 5237,
      "a500m_best": 0,
      "1h_best": 0,
      "spot": "",
      "wind": "",
      "board": "",
      "sail": "",
      "fin": ""
    },
    {
      "file": "/logs/2024/10/0607_2024-10-15-1008.oao",
      "size": 963224,
      "timezone": 60,
      "mode": 0,
      "start_date": 1728983319000,
      "end_date": 1729007835000,
      "duration": 24516000,
      "distance": 29083039,
      "2s_best": 10436,
      "10s_best": 9756,
      "500m_best": 8123,
      "1852m_best": 7057,
      "a500m_best": 5250,
      "1h_best": 1738,
      "spot": "",
      "wind": "",
      "board": "",
      "sail": "",
      "fin": ""
    }
  ]
}