{
  "CAR853MAR_853_20231011_113150.oao": {
    "motion_file": "/logs/2023/10/0853_2023-10-11-1131.oao",
    "local_file": "/home/jovyan/work/sse-results/events/2023/gpslogs/20231011/CAR853MAR_853_20231011_113150.oao",
    "size": 685336,
    "start_date": 1697020310000,
    "end_date": 1697032378000,
    "duration": 12068000,
    "distance": 20273736,
    "2s_best": 23070,
    "10s_best": 22708,
    "500m_best": 22555,
    "status": "completed"
  },
  "BUK853MAC_853_20241012_104819.oao": {
    "motion_file": "/logs/2024/10/0853_2024-10-12-1048.oao",
    "local_file": "/home/jovyan/work/sse-results/events/2024/gpslogs/20241012/BUK853MAC_853_20241012_104819.oao",
    "size": 7256,
    "start_date": 1728726499000,
    "end_date": 1728745547000,
    "duration": 19048000,
    "distance": 4155731,
    "2s_best": 1886,
    "10s_best": 1645,
    "500m_best": 0,
    "status": "skipped"
  },
  "BUK853MAC_853_20241013_135727.oao": {
    "motion_file": "/logs/2024/10/0853_2024-10-13-1357.oao",
    "local_file": "/home/jovyan/work/sse-results/events/2024/gpslogs/20241013/BUK853MAC_853_20241013_135727.oao",
    "size": 6736,
    "start_date": 1728824247000,
    "end_date": 1728825981000,
    "duration": 1734000,
    "distance": 592140,
    "2s_best": 3809,
    "10s_best": 1250,
    "500m_best": 0,
    "status": "skipped"
  },
  "BUK853MAC_853_20241014_105647.oao": {
    "motion_file": "/logs/2024/10/0853_2024-10-14-1056.oao",
    "local_file": "/home/jovyan/work/sse-results/events/2024/gpslogs/20241014/BUK853MAC_853_20241014_105647.oao",
    "size": 18176,
    "start_date": 1728899807000,
    "end_date": 1728914479000,
    "duration": 14672000,
    "distance": 2956349,
    "2s_best": 2189,
    "10s_best": 1963,
    "500m_best": 0,
    "status": "skipped"
  },
  "BUK853MAC_853_20241015_100939.oao": {
    "motion_file": "/logs/2024/10/0853_2024-10-15-1009.oao",
    "local_file": "/home/jovyan/work/sse-results/events/2024/gpslogs/20241015/BUK853MAC_853_20241015_100939.oao",
    "size": 2460720,
    "start_date": 1728983379000,
    "end_date": 1729008595000,
    "duration": 25216000,
    "distance": 63627458,
    "2s_best": 13259,
    "10s_best": 12989,
    "500m_best": 12334,
    "status": "completed"
  },
  "BUK853MAC_853_20241016_105703.oao": {
    "motion_file": "/logs/2024/10/0853_2024-10-16-1057.oao",
    "local_file": "/home/jovyan/work/sse-results/events/2024/gpslogs/20241016/BUK853MAC_853_20241016_105703.oao",
    "size": 1002588,
    "start_date": 1729072623000,
    "end_date": 1729085771000,
    "duration": 13148000,
    "distance": 22924203,
    "2s_best": 7866,
    "10s_best": 7618,
    "500m_best": 6346,
    "status": "completed"
  },
  "BUK853MAC_853_20241017_103701.oao": {
    "motion_file": "/logs/2024/10/0853_2024-10-17-1037.oao",
    "local_file": "/home/jovyan/work/sse-results/events/2024/gpslogs/20241017/BUK853MAC_853_20241017_103701.oao",
    "size": 2807404,
    "start_date": 1729157821000,
    "end_date": 1729181461000,
    "duration": 23640000,
    "distance": 59500624,
    "2s_best": 11696,
    "10s_best": 11344,
    "500m_best": 10778,
    "status": "completed"
  },
  "BUK853MAC_853_20241018_113409.oao": {
    "motion_file": "/logs/2024/10/0853_2024-10-18-1134.oao",
    "local_file": "/home/jovyan/work/sse-results/events/2024/gpslogs/20241018/BUK853MAC_853_20241018_113409.oao",
    "size": 1761060,
    "start_date": 1729247649000,
    "end_date": 1729267467000,
    "duration": 19818000,
    "distance": 53854234,
    "2s_best": 13417,
    "10s_best": 13138,
    "500m_best": 12820,
    "status": "completed"
  },
  "DIC853FIN_853_20241012_104819.oao": {
    "motion_file": "/logs/2024/10/0853_2024-10-12-1048.oao",
    "local_file": "/home/jovyan/work/sse-results/events/2025/gpslogs/20241012/DIC853FIN_853_20241012_104819.oao",
    "size": 7256,
    "start_date": 1728726499000,
    "end_date": 1728745547000,
    "duration": 19048000,
    "distance": 4155731,
    "2s_best": 1886,
    "10s_best": 1645,
    "500m_best": 0,
    "status": "skipped"
  },
  "DIC853FIN_853_20241013_135727.oao": {
    "motion_file": "/logs/2024/10/0853_2024-10-13-1357.oao",
    "local_file": "/home/jovyan/work/sse-results/events/2025/gpslogs/20241013/DIC853FIN_853_20241013_135727.oao",
    "size": 6736,
    "start_date": 1728824247000,
    "end_date": 1728825981000,
    "duration": 1734000,
    "distance": 592140,
    "2s_best": 3809,
    "10s_best": 1250,
    "500m_best": 0,
    "status": "skipped"
  },
  "DIC853FIN_853_20241014_105647.oao": {
    "motion_file": "/logs/2024/10/0853_2024-10-14-1056.oao",
    "local_file": "/home/jovyan/work/sse-results/events/2025/gpslogs/20241014/DIC853FIN_853_20241014_105647.oao",
    "size": 18176,
    "start_date": 1728899807000,
    "end_date": 1728914479000,
    "duration": 14672000,
    "distance": 2956349,
    "2s_best": 2189,
    "10s_best": 1963,
    "500m_best": 0,
    "status": "skipped"
  },
  "DIC853FIN_853_20241015_100939.oao": {
    "motion_file": "/logs/2024/10/0853_2024-10-15-1009.oao",
    "local_file": "/home/jovyan/work/sse-results/events/2025/gpslogs/20241015/DIC853FIN_853_20241015_100939.oao",
    "size": 2460720,
    "start_date": 1728983379000,
    "end_date": 1729008595000,
    "duration": 25216000,
    "distance": 63627458,
    "2s_best": 13259,
    "10s_best": 12989,
    "500m_best": 12334,
    "status": "completed"
  },
  "DIC853FIN_853_20241016_105703.oao": {
    "motion_file": "/logs/2024/10/0853_2024-10-16-1057.oao",
    "local_file": "/home/jovyan/work/sse-results/events/2025/gpslogs/20241016/DIC853FIN_853_20241016_105703.oao",
    "size": 1002588,
    "start_date": 1729072623000,
    "end_date": 1729085771000,
    "duration": 13148000,
    "distance": 22924203,
    "2s_best": 7866,
    "10s_best": 7618,
    "500m_best": 6346,
    "status": "completed"
  },
  "DIC853FIN_853_20241017_103701.oao": {
    "motion_file": "/logs/2024/10/0853_2024-10-17-1037.oao",
    "local_file": "/home/jovyan/work/sse-results/events/2025/gpslogs/20241017/DIC853FIN_853_20241017_103701.oao",
    "size": 2807404,
    "start_date": 1729157821000,
    "end_date": 1729181461000,
    "duration": 23640000,
    "distance": 59500624,
    "2s_best": 11696,
    "10s_best": 11344,
    "500m_best": 10778,
    "status": "completed"
  },
  "DIC853FIN_853_20241018_113409.oao": {
    "motion_file": "/logs/2024/10/0853_2024-10-18-1134.oao",
    "local_file": "/home/jovyan/work/sse-results/events/2025/gpslogs/20241018/DIC853FIN_853_20241018_113409.oao",
    "size": 1761060,
    "start_date": 1729247649000,
    "end_date": 1729267467000,
    "duration": 19818000,
    "distance": 53854234,
    "2s_best": 13417,
    "10s_best": 13138,
    "500m_best": 12820,
    "status": "completed"
  }
}