{
  "VAN119PAT_641_20221015_113410.oao": {
    "motion_file": "/logs/2022/10/0641_2022-10-15-1134.oao",
    "local_file": "/home/jovyan/work/sse-results/events/2022/gpslogs/20221015/VAN119PAT_641_20221015_113410.oao",
    "size": 1700896,
    "start_date": 1665830050000,
    "end_date": 1665851970000,
    "duration": 21920000,
    "distance": 75860449,
    "2s_best": 18907,
    "10s_best": 18333,
    "500m_best": 17752,
    "status": "completed"
  },
  "VAN119PAT_641_20221017_100546.oao": {
    "motion_file": "/logs/2022/10/0641_2022-10-17-1005.oao",
    "local_file": "/home/jovyan/work/sse-results/events/2022/gpslogs/20221017/VAN119PAT_641_20221017_100546.oao",
    "size": 750336,
    "start_date": 1665997546000,
    "end_date": 1666008930000,
    "duration": 11384000,
    "distance": 33087821,
    "2s_best": 15261,
    "10s_best": 14971,
    "500m_best": 14401,
    "status": "completed"
  },
  "VAN119PAT_641_20221017_135326.oao": {
    "motion_file": "/logs/2022/10/0641_2022-10-17-1353.oao",
    "local_file": "/home/jovyan/work/sse-results/events/2022/gpslogs/20221017/VAN119PAT_641_20221017_135326.oao",
    "size": 1536,
    "start_date": 1666011206000,
    "end_date": 1666011352000,
    "duration": 146000,
    "distance": 26725,
    "2s_best": 0,
    "10s_best": 0,
    "500m_best": 0,
    "status": "skipped"
  },
  "VAN119PAT_641_20221018_130948.oao": {
    "motion_file": "/logs/2022/10/0641_2022-10-18-1309.oao",
    "local_file": "/home/jovyan/work/sse-results/events/2022/gpslogs/20221018/VAN119PAT_641_20221018_130948.oao",
    "size": 1744264,
    "start_date": 1666094988000,
    "end_date": 1666108720000,
    "duration": 13732000,
    "distance": 72104666,
    "2s_best": 16130,
    "10s_best": 15909,
    "500m_best": 15397,
    "status": "completed"
  },
  "VAN119PAT_641_20221019_111450.oao": {
    "motion_file": "/logs/2022/10/0641_2022-10-19-1114.oao",
    "local_file": "/home/jovyan/work/sse-results/events/2022/gpslogs/20221019/VAN119PAT_641_20221019_111450.oao",
    "size": 1579580,
    "start_date": 1666174490000,
    "end_date": 1666194888000,
    "duration": 20398000,
    "distance": 56937472,
    "2s_best": 17061,
    "10s_best": 16742,
    "500m_best": 16164,
    "status": "completed"
  },
  "CUN641CHR_641_20231007_102410.oao": {
    "motion_file": "/logs/2023/10/0641_2023-10-07-1024.oao",
    "local_file": "/home/jovyan/work/sse-results/events/2023/gpslogs/20231007/CUN641CHR_641_20231007_102410.oao",
    "size": 1949092,
    "start_date": 1696670650000,
    "end_date": 1696689128000,
    "duration": 18478000,
    "distance": 59198589,
    "2s_best": 11018,
    "10s_best": 10828,
    "500m_best": 10510,
    "status": "completed"
  },
  "CUN641CHR_641_20231010_094502.oao": {
    "motion_file": "/logs/2023/10/0641_2023-10-10-0945.oao",
    "local_file": "/home/jovyan/work/sse-results/events/2023/gpslogs/20231010/CUN641CHR_641_20231010_094502.oao",
    "size": 1919660,
    "start_date": 1696927502000,
    "end_date": 1696949458000,
    "duration": 21956000,
    "distance": 64712079,
    "2s_best": 11845,
    "10s_best": 11628,
    "500m_best": 11397,
    "status": "completed"
  },
  "CUN641CHR_641_20231011_091416.oao": {
    "motion_file": "/logs/2023/10/0641_2023-10-11-0914.oao",
    "local_file": "/home/jovyan/work/sse-results/events/2023/gpslogs/20231011/CUN641CHR_641_20231011_091416.oao",
    "size": 3547000,
    "start_date": 1697012056000,
    "end_date": 1697037256000,
    "duration": 25200000,
    "distance": 110304481,
    "2s_best": 12289,
    "10s_best": 11813,
    "500m_best": 11493,
    "status": "completed"
  },
  "CUN641CHR_641_20231012_094140.oao": {
    "motion_file": "/logs/2023/10/0641_2023-10-12-0941.oao",
    "local_file": "/home/jovyan/work/sse-results/events/2023/gpslogs/20231012/CUN641CHR_641_20231012_094140.oao",
    "size": 2102076,
    "start_date": 1697100100000,
    "end_date": 1697123888000,
    "duration": 23788000,
    "distance": 69783994,
    "2s_best": 13158,
    "10s_best": 12398,
    "500m_best": 12182,
    "status": "completed"
  },
  "CUN641CHR_641_20231013_084002.oao": {
    "motion_file": "/logs/2023/10/0641_2023-10-13-0840.oao",
    "local_file": "/home/jovyan/work/sse-results/events/2023/gpslogs/20231013/CUN641CHR_641_20231013_084002.oao",
    "size": 2114816,
    "start_date": 1697182802000,
    "end_date": 1697205638000,
    "duration": 22836000,
    "distance": 66610509,
    "2s_best": 12609,
    "10s_best": 12380,
    "500m_best": 11761,
    "status": "completed"
  },
  "BUR641EMI_641_20241012_110751.oao": {
    "motion_file": "/logs/2024/10/0641_2024-10-12-1107.oao",
    "local_file": "/home/jovyan/work/sse-results/events/2024/gpslogs/20241012/BUR641EMI_641_20241012_110751.oao",
    "size": 2005668,
    "start_date": 1728727671000,
    "end_date": 1728750805000,
    "duration": 23134000,
    "distance": 63940393,
    "2s_best": 19595,
    "10s_best": 19548,
    "500m_best": 19307,
    "status": "completed"
  },
  "BUR641EMI_641_20241014_101655.oao": {
    "motion_file": "/logs/2024/10/0641_2024-10-14-1016.oao",
    "local_file": "/home/jovyan/work/sse-results/events/2024/gpslogs/20241014/BUR641EMI_641_20241014_101655.oao",
    "size": 1880140,
    "start_date": 1728897415000,
    "end_date": 1728917001000,
    "duration": 19586000,
    "distance": 57654407,
    "2s_best": 21393,
    "10s_best": 21063,
    "500m_best": 19600,
    "status": "completed"
  },
  "BUR641EMI_641_20241015_121049.oao": {
    "motion_file": "/logs/2024/10/0641_2024-10-15-1210.oao",
    "local_file": "/home/jovyan/work/sse-results/events/2024/gpslogs/20241015/BUR641EMI_641_20241015_121049.oao",
    "size": 1597260,
    "start_date": 1728990649000,
    "end_date": 1729006767000,
    "duration": 16118000,
    "distance": 52406052,
    "2s_best": 21282,
    "10s_best": 21167,
    "500m_best": 20795,
    "status": "completed"
  },
  "BUR641EMI_641_20241016_113608.oao": {
    "motion_file": "/logs/2024/10/0641_2024-10-16-1136.oao",
    "local_file": "/home/jovyan/work/sse-results/events/2024/gpslogs/20241016/BUR641EMI_641_20241016_113608.oao",
    "size": 1286300,
    "start_date": 1729074968000,
    "end_date": 1729090711000,
    "duration": 15743000,
    "distance": 36392060,
    "2s_best": 20045,
    "10s_best": 19722,
    "500m_best": 19039,
    "status": "completed"
  }
}